cycless/__init__.py
cycless/cycles.py
cycless/dicycles.py
cycless/polyhed.py
cycless/rings.py
cycless/simplex.py
cycless-0.6.3.dist-info/METADATA
cycless-0.6.3.dist-info/WHEEL
cycless-0.6.3.dist-info/RECORD
