Metadata-Version: 2.1
Name: cycless
Version: 0.6.3
Summary: A collection of algorithms for cycles in a graph.
License: MIT
Author: vitroid
Author-email: vitroid@gmail.com
Requires-Python: >=3.10,<4.0
Classifier: License :: OSI Approved :: MIT License
Classifier: Programming Language :: Python :: 3
Classifier: Programming Language :: Python :: 3.10
Classifier: Programming Language :: Python :: 3.11
Classifier: Programming Language :: Python :: 3.12
Requires-Dist: click (>=8)
Requires-Dist: methodtools (>=0.4.7,<0.5.0)
